xmltread/__init__.py
xmltread/seeder.py
xmltread/utils.py
xmltread/xmltramp.py
xmltread-0.3.dist-info/LICENSE
xmltread-0.3.dist-info/METADATA
xmltread-0.3.dist-info/WHEEL
xmltread-0.3.dist-info/top_level.txt
xmltread-0.3.dist-info/RECORD
