Metadata-Version: 2.1
Name: xmltread
Version: 0.3
Summary: Make XML documents more easily accessible
Author-email: Aaron Swartz <me@aaronsw.com>, Paul Jimenez <pj@place.org>
License: GNU GENERAL PUBLIC LICENSE
Project-URL: Homepage, http://github.com/pjz/xmltread
Project-URL: Documentation, http://pjz.github.io/xmltread
Project-URL: Repository, http://github.com/pjz/xmltread.git
Classifier: Intended Audience :: Developers
Classifier: License :: OSI Approved :: GNU General Public License v2 (GPLv2)
Classifier: Operating System :: OS Independent
Classifier: Programming Language :: Python :: 3
Classifier: Programming Language :: Python :: 3.8
Classifier: Programming Language :: Python :: 3.9
Classifier: Programming Language :: Python :: 3.10
Classifier: Programming Language :: Python :: 3.11
Classifier: Topic :: Text Processing :: Markup :: XML
Requires-Python: >=3.8
License-File: LICENSE
Provides-Extra: dev
Requires-Dist: pytest ; extra == 'dev'
Requires-Dist: pytest-mypy ; extra == 'dev'
Requires-Dist: black ; extra == 'dev'
Requires-Dist: build ; extra == 'dev'
Requires-Dist: twine ; extra == 'dev'
